README.md
setup.py
codegen/__init__.py
codegen/db.py
codegen/main.py
codegen/typez.py
codegen/define/__init__.py
codegen/define/python_define.py
codegen/define/scala_define.py
demo/__init__.py
demo/db_fns.py
demo/main.py
demo/demo_controllers/__init__.py
demo/demo_controllers/big_controller.py
demo/shared/__init__.py
demo/shared/db_fns.py
demo/shared/db_views.py
webskeleton/__init__.py
webskeleton/appredis.py
webskeleton/auth.py
webskeleton/autheval.py
webskeleton/bootstrap.py
webskeleton/core.py
webskeleton/db.py
webskeleton/env.py
webskeleton/py.typed
webskeleton/request.py
webskeleton/typez.py
webskeleton.egg-info/PKG-INFO
webskeleton.egg-info/SOURCES.txt
webskeleton.egg-info/dependency_links.txt
webskeleton.egg-info/requires.txt
webskeleton.egg-info/top_level.txt