Metadata-Version: 1.1
Name: webskeleton
Version: 0.1.0
Summary: Web skeleton
Home-page: https://github.com/tengelisconsulting/webskeleton
Author: Liam Tengelis
Author-email: liam@tengelisconsulting.com
License: UNKNOWN
Download-URL: https://github.com/tengelisconsulting/webskeleton/archive/v0.1.0.tar.gz
Platform: UNKNOWN
